bcp47/__init__.py
bcp47/code.py
bcp47/exceptions.py
bcp47/iana-bcp47.txt
bcp47/parser.py
tests/__init__.py
tests/bcp47.py
tests/code.py
tests/parser.py
python_bcp47-0.0.4.dist-info/METADATA
python_bcp47-0.0.4.dist-info/WHEEL
python_bcp47-0.0.4.dist-info/top_level.txt
python_bcp47-0.0.4.dist-info/RECORD
