Metadata-Version: 2.1
Name: python-bcp47
Version: 0.0.4
Summary: Parser and validator for language codes (bcp47). Also exposes the IANA language code database
Home-page: https://github.com/phlax/bcp47
Author: Ryan Northey
Author-email: ryan@synca.io
License: GPL3
Project-URL: Source, https://github.com/phlax/python-bcp47/
Platform: UNKNOWN
Classifier: Development Status :: 4 - Beta
Classifier: Intended Audience :: Developers
Classifier: License :: OSI Approved :: GNU General Public License v3 or later (GPLv3+)
Classifier: Operating System :: OS Independent
Classifier: Programming Language :: Python
Classifier: Programming Language :: Python :: 3
Classifier: Topic :: Software Development :: Libraries :: Python Modules
Provides-Extra: test
Requires-Dist: flake8 (==2.4.1) ; extra == 'test'
Requires-Dist: pytest ; extra == 'test'
Requires-Dist: pytest-cov ; extra == 'test'
Requires-Dist: codecov ; extra == 'test'
